search_in_a_third/__init__.py
search_in_a_third/search_in_a_third.py
search_in_a_third-0.1.1.dist-info/LICENSE
search_in_a_third-0.1.1.dist-info/METADATA
search_in_a_third-0.1.1.dist-info/WHEEL
search_in_a_third-0.1.1.dist-info/top_level.txt
search_in_a_third-0.1.1.dist-info/RECORD
