Metadata-Version: 2.1
Name: search_in_a_third
Version: 0.1.1
Summary: A Python package for efficient hyperparameter optimization in neural networks, using a greedy algorithm guided by heuristic directions.
Home-page: https://github.com/proflarriera/searchinathird
Author: Diego Larriera
Author-email: proflarriera@gmail.com
License: MIT
Keywords: hyperparameter optimization,neural networks,machine learning,greedy algorithm,heuristic
Classifier: Programming Language :: Python :: 3
Classifier: License :: OSI Approved :: MIT License
Classifier: Intended Audience :: Developers
Classifier: Topic :: Software Development :: Libraries :: Python Modules
License-File: LICENSE
Requires-Dist: tensorflow
Requires-Dist: scikit-learn
Requires-Dist: pandas
